bookman/__init__.py
bookman/__main__.py
bookman/bookman.py
bookman/controllers.py
bookman/domains.py
bookman/models.py
bookman/services.py
bookman/settings.py
bookman/utils.py
lodek_bookman-0.4.0.dist-info/entry_points.txt
lodek_bookman-0.4.0.dist-info/WHEEL
lodek_bookman-0.4.0.dist-info/METADATA
lodek_bookman-0.4.0.dist-info/RECORD
