Metadata-Version: 2.1
Name: lodek-bookman
Version: 0.4.0
Summary: Small CLI tool to manage a local library.
Home-page: https://github.com/Lodek/bookman
Author: Bruno Gomes
Author-email: lodek@protonmail.com
Requires-Python: >=3.8,<4.0
Classifier: Programming Language :: Python :: 3
Classifier: Programming Language :: Python :: 3.8
Classifier: Programming Language :: Python :: 3.9
Requires-Dist: requests (>=2.25.1,<3.0.0)
Project-URL: Repository, https://github.com/Lodek/bookman
